Metadata-Version: 2.1
Name: nonebot-plugin-answersbook
Version: 0.2.0
Summary: The Book of Answers for NoneBot2
License: MIT
Author-email: Akirami <Akiramiaya@outlook.com>
Requires-Python: >=3.8
Requires-Dist: nonebot-adapter-onebot>=2.0.0b1
Requires-Dist: nonebot2>=2.0.0b2
Project-URL: Homepage, https://github.com/A-kirami/nonebot-plugin-answersbook
Project-URL: Repository, https://github.com/A-kirami/nonebot-plugin-answersbook
